tomapi/__init__.py
tomapi/api.py
tomapi/middleware.py
tomapi/response.py
tomapi-0.0.2.dist-info/METADATA
tomapi-0.0.2.dist-info/WHEEL
tomapi-0.0.2.dist-info/top_level.txt
tomapi-0.0.2.dist-info/RECORD
